saqqarah/AboutUIClass.py
saqqarah/LICENSE
saqqarah/ParametersClass.py
saqqarah/PreferencesUIClass.py
saqqarah/PyramidClass.py
saqqarah/PyramidPrinterClass.py
saqqarah/PyramidPrinterImageClass.py
saqqarah/PyramidPrinterTikzClass.py
saqqarah/SaqqarahUIClass.py
saqqarah/__QT5__.py
saqqarah/__init__.py
saqqarah/__main__.py
saqqarah/gpl-v3.0.txt
saqqarah/saqqarah-qt.py
saqqarah/test_introspection.py
saqqarah/tools.py
saqqarah/version.py
saqqarah/fonts/AerialBd.ttf
saqqarah/fonts/Bitstream-Vera-Copyright.txt
saqqarah/fonts/__init__.py
saqqarah/ui/__init__.py
saqqarah/ui/about.ui
saqqarah/ui/preferences.ui
saqqarah/ui/saqqarah-qt.ui
saqqarah-1.0.1.dist-info/LICENSE
saqqarah-1.0.1.dist-info/METADATA
saqqarah-1.0.1.dist-info/WHEEL
saqqarah-1.0.1.dist-info/entry_points.txt
saqqarah-1.0.1.dist-info/top_level.txt
saqqarah-1.0.1.dist-info/RECORD
