Metadata-Version: 2.1
Name: saqqarah
Version: 1.0.1
Summary: Calculation pyramid generator
Home-page: https://framagit.org/ycombe/saqqarah
Author: Yves Combe
Author-email: yves@ycombe.net
License: UNKNOWN
Keywords: mathematics,addition,pyramid,school
Platform: UNKNOWN
Classifier: Development Status :: 5 - Production/Stable
Classifier: Environment :: Console
Classifier: Environment :: X11 Applications :: Qt
Classifier: Intended Audience :: Education
Classifier: License :: DFSG approved
Classifier: License :: OSI Approved :: GNU General Public License v3 or later (GPLv3+)
Classifier: Topic :: Education
Requires-Python: >=3.6
Requires-Dist: Pillow
Requires-Dist: PySide2
Requires-Dist: numpy
